README
setup.py
comicnamer/__init__.py
comicnamer/cliarg_parser.py
comicnamer/comicnamer_exceptions.py
comicnamer/config.py
comicnamer/config_defaults.py
comicnamer/main.py
comicnamer/unicode_helper.py
comicnamer/utils.py
comicnamer.egg-info/PKG-INFO
comicnamer.egg-info/SOURCES.txt
comicnamer.egg-info/dependency_links.txt
comicnamer.egg-info/entry_points.txt
comicnamer.egg-info/requires.txt
comicnamer.egg-info/top_level.txt