Metadata-Version: 1.0
Name: comicnamer
Version: 1.0
Summary: Automatic TV episode file renamer, uses data from thetvdb.com via tvdb_api
Home-page: http://github.com/swc/comicnamer
Author: swc/Steve
Author-email: iam@attractive.com
License: GPLv2
Platform: UNKNOWN
Classifier: Environment :: Console
Classifier: Intended Audience :: End Users/Desktop
Classifier: License :: OSI Approved :: GNU General Public License (GPL)
Classifier: Natural Language :: English
Classifier: Operating System :: OS Independent
Classifier: Programming Language :: Python
Classifier: Topic :: Multimedia
Classifier: Topic :: Utilities
